aidge_onnx/__init__.py
aidge_onnx/compare_to_ort.py
aidge_onnx/dtype_converter.py
aidge_onnx/generate_singleop_onnx.py
aidge_onnx/onnx_cleaner.py
aidge_onnx/onnx_export.py
aidge_onnx/onnx_import.py
aidge_onnx/onnx_test.py
aidge_onnx/ort_inferences.py
aidge_onnx/utils.py
aidge_onnx/node_export/__init__.py
aidge_onnx/node_export/aidge_converter.py
aidge_onnx/node_export/generic_export.py
aidge_onnx/node_export/aidge_converters/__init__.py
aidge_onnx/node_export/aidge_converters/abs.py
aidge_onnx/node_export/aidge_converters/add.py
aidge_onnx/node_export/aidge_converters/and.py
aidge_onnx/node_export/aidge_converters/argmax.py
aidge_onnx/node_export/aidge_converters/atan.py
aidge_onnx/node_export/aidge_converters/average_pool.py
aidge_onnx/node_export/aidge_converters/batchnorm.py
aidge_onnx/node_export/aidge_converters/bitshift.py
aidge_onnx/node_export/aidge_converters/cast.py
aidge_onnx/node_export/aidge_converters/ceil.py
aidge_onnx/node_export/aidge_converters/clip.py
aidge_onnx/node_export/aidge_converters/concat.py
aidge_onnx/node_export/aidge_converters/constantofshape.py
aidge_onnx/node_export/aidge_converters/conv.py
aidge_onnx/node_export/aidge_converters/convtranspose.py
aidge_onnx/node_export/aidge_converters/dequantize_linear.py
aidge_onnx/node_export/aidge_converters/div.py
aidge_onnx/node_export/aidge_converters/dropout.py
aidge_onnx/node_export/aidge_converters/equal.py
aidge_onnx/node_export/aidge_converters/erf.py
aidge_onnx/node_export/aidge_converters/exp.py
aidge_onnx/node_export/aidge_converters/expand.py
aidge_onnx/node_export/aidge_converters/fc.py
aidge_onnx/node_export/aidge_converters/flatten.py
aidge_onnx/node_export/aidge_converters/floor.py
aidge_onnx/node_export/aidge_converters/gather.py
aidge_onnx/node_export/aidge_converters/gelu.py
aidge_onnx/node_export/aidge_converters/gemm.py
aidge_onnx/node_export/aidge_converters/globalaveragepooling.py
aidge_onnx/node_export/aidge_converters/hardmax.py
aidge_onnx-0.7.0.dist-info/licenses/LICENSE
aidge_onnx-0.7.0.dist-info/METADATA
aidge_onnx-0.7.0.dist-info/WHEEL
aidge_onnx-0.7.0.dist-info/entry_points.txt
aidge_onnx-0.7.0.dist-info/top_level.txt
aidge_onnx-0.7.0.dist-info/RECORD
