Metadata-Version: 2.4
Name: aidge_onnx
Version: 0.7.0
Summary: Aidge bridge to onnx framework, contains algorithms to import and export models.
License: Eclipse Public License - v 2.0
Project-URL: Homepage, https://www.deepgreen.ai/en/platform
Project-URL: Documentation, https://eclipse.dev/aidge/
Project-URL: Repository, https://gitlab.eclipse.org/eclipse/aidge/aidge_onnx
Project-URL: Issues, https://gitlab.eclipse.org/eclipse/aidge/aidge_onnx/-/issues/
Project-URL: Changelog, https://gitlab.eclipse.org/eclipse/aidge/aidge_onnx/-/releases
Classifier: Development Status :: 2 - Pre-Alpha
Classifier: Programming Language :: Python :: 3
Requires-Python: >=3.10
License-File: LICENSE
Requires-Dist: numpy>=1.20
Requires-Dist: onnx>=1.16.0
Requires-Dist: colorama
Requires-Dist: typing_extensions
Requires-Dist: rich
Provides-Extra: test
Requires-Dist: pytest; extra == "test"
Requires-Dist: requests; extra == "test"
Requires-Dist: matplotlib; extra == "test"
Requires-Dist: onnxruntime>=1.18.0; extra == "test"
Dynamic: license-file
